{"minutiae": [{"x": 81, "y": 199, "type": "ending"}, {"x": 82, "y": 199, "type": "bifurcation"}, {"x": 84, "y": 204, "type": "ending"}, {"x": 88, "y": 208, "type": "ending"}, {"x": 89, "y": 189, "type": "bifurcation"}, {"x": 90, "y": 191, "type": "ending"}, {"x": 93, "y": 213, "type": "ending"}, {"x": 94, "y": 225, "type": "ending"}, {"x": 96, "y": 169, "type": "ending"}, {"x": 97, "y": 157, "type": "ending"}, {"x": 98, "y": 121, "type": "ending"}, {"x": 98, "y": 133, "type": "ending"}, {"x": 98, "y": 145, "type": "ending"}, {"x": 98, "y": 226, "type": "ending"}, {"x": 99, "y": 133, "type": "bifurcation"}, {"x": 99, "y": 217, "type": "bifurcation"}, {"x": 100, "y": 135, "type": "ending"}, {"x": 101, "y": 117, "type": "ending"}, {"x": 102, "y": 232, "type": "ending"}, {"x": 103, "y": 115, "type": "ending"}, {"x": 107, "y": 238, "type": "ending"}, {"x": 110, "y": 272, "type": "ending"}, {"x": 123, "y": 434, "type": "ending"}, {"x": 124, "y": 314, "type": "ending"}, {"x": 124, "y": 324, "type": "ending"}, {"x": 128, "y": 428, "type": "ending"}, {"x": 132, "y": 94, "type": "ending"}, {"x": 135, "y": 429, "type": "bifurcation"}, {"x": 136, "y": 295, "type": "ending"}, {"x": 136, "y": 432, "type": "bifurcation"}, {"x": 137, "y": 425, "type": "bifurcation"}, {"x": 138, "y": 293, "type": "ending"}, {"x": 138, "y": 339, "type": "ending"}, {"x": 138, "y": 427, "type": "ending"}, {"x": 139, "y": 291, "type": "bifurcation"}, {"x": 140, "y": 253, "type": "bifurcation"}, {"x": 140, "y": 349, "type": "ending"}, {"x": 140, "y": 357, "type": "ending"}, {"x": 140, "y": 363, "type": "ending"}, {"x": 140, "y": 373, "type": "ending"}, {"x": 140, "y": 394, "type": "ending"}, {"x": 140, "y": 400, "type": "ending"}, {"x": 140, "y": 401, "type": "ending"}, {"x": 140, "y": 403, "type": "ending"}, {"x": 140, "y": 404, "type": "ending"}, {"x": 140, "y": 441, "type": "ending"}, {"x": 141, "y": 364, "type": "bifurcation"}, {"x": 141, "y": 439, "type": "bifurcation"}, {"x": 142, "y": 150, "type": "ending"}, {"x": 142, "y": 247, "type": "bifurcation"}, {"x": 142, "y": 337, "type": "ending"}, {"x": 142, "y": 396, "type": "ending"}, {"x": 142, "y": 441, "type": "ending"}, {"x": 143, "y": 335, "type": "bifurcation"}, {"x": 143, "y": 427, "type": "bifurcation"}, {"x": 143, "y": 437, "type": "bifurcation"}, {"x": 144, "y": 412, "type": "ending"}, {"x": 144, "y": 424, "type": "ending"}, {"x": 144, "y": 429, "type": "ending"}, {"x": 144, "y": 439, "type": "ending"}, {"x": 146, "y": 396, "type": "ending"}, {"x": 147, "y": 433, "type": "bifurcation"}, {"x": 147, "y": 442, "type": "ending"}, {"x": 148, "y": 392, "type": "bifurcation"}, {"x": 148, "y": 395, "type": "ending"}, {"x": 148, "y": 409, "type": "ending"}, {"x": 148, "y": 436, "type": "ending"}, {"x": 149, "y": 405, "type": "bifurcation"}, {"x": 149, "y": 407, "type": "bifurcation"}, {"x": 150, "y": 246, "type": "ending"}, {"x": 150, "y": 346, "type": "ending"}, {"x": 152, "y": 236, "type": "ending"}, {"x": 152, "y": 240, "type": "ending"}, {"x": 152, "y": 293, "type": "ending"}, {"x": 152, "y": 380, "type": "ending"}, {"x": 153, "y": 291, "type": "bifurcation"}, {"x": 155, "y": 445, "type": "ending"}, {"x": 156, "y": 421, "type": "ending"}, {"x": 157, "y": 351, "type": "bifurcation"}, {"x": 158, "y": 88, "type": "bifurcation"}, {"x": 158, "y": 99, "type": "bifurcation"}, {"x": 158, "y": 389, "type": "bifurcation"}, {"x": 158, "y": 401, "type": "ending"}, {"x": 159, "y": 100, "type": "ending"}, {"x": 159, "y": 235, "type": "bifurcation"}, {"x": 159, "y": 349, "type": "bifurcation"}, {"x": 159, "y": 360, "type": "ending"}, {"x": 159, "y": 385, "type": "ending"}, {"x": 160, "y": 356, "type": "ending"}, {"x": 160, "y": 441, "type": "bifurcation"}, {"x": 161, "y": 442, "type": "ending"}, {"x": 162, "y": 82, "type": "ending"}, {"x": 162, "y": 90, "type": "ending"}, {"x": 162, "y": 362, "type": "bifurcation"}, {"x": 162, "y": 364, "type": "ending"}, {"x": 163, "y": 83, "type": "bifurcation"}, {"x": 164, "y": 365, "type": "ending"}, {"x": 165, "y": 363, "type": "bifurcation"}, {"x": 166, "y": 92, "type": "ending"}, {"x": 166, "y": 95, "type": "bifurcation"}, {"x": 166, "y": 369, "type": "ending"}, {"x": 166, "y": 372, "type": "bifurcation"}, {"x": 167, "y": 223, "type": "bifurcation"}, {"x": 168, "y": 225, "type": "ending"}, {"x": 168, "y": 278, "type": "ending"}, {"x": 169, "y": 276, "type": "bifurcation"}, {"x": 170, "y": 386, "type": "ending"}, {"x": 170, "y": 430, "type": "ending"}, {"x": 171, "y": 163, "type": "bifurcation"}, {"x": 172, "y": 165, "type": "ending"}, {"x": 172, "y": 379, "type": "ending"}, {"x": 172, "y": 426, "type": "ending"}, {"x": 173, "y": 376, "type": "bifurcation"}, {"x": 174, "y": 382, "type": "ending"}, {"x": 175, "y": 108, "type": "bifurcation"}, {"x": 175, "y": 178, "type": "bifurcation"}, {"x": 175, "y": 388, "type": "bifurcation"}, {"x": 176, "y": 378, "type": "ending"}, {"x": 176, "y": 399, "type": "bifurcation"}, {"x": 177, "y": 369, "type": "bifurcation"}, {"x": 177, "y": 390, "type": "bifurcation"}, {"x": 178, "y": 105, "type": "ending"}, {"x": 178, "y": 179, "type": "ending"}, {"x": 178, "y": 372, "type": "ending"}, {"x": 178, "y": 401, "type": "ending"}, {"x": 179, "y": 424, "type": "ending"}, {"x": 180, "y": 88, "type": "ending"}, {"x": 180, "y": 93, "type": "ending"}, {"x": 180, "y": 390, "type": "ending"}, {"x": 183, "y": 176, "type": "ending"}, {"x": 183, "y": 382, "type": "ending"}, {"x": 184, "y": 180, "type": "ending"}, {"x": 184, "y": 378, "type": "ending"}, {"x": 184, "y": 382, "type": "ending"}, {"x": 184, "y": 384, "type": "ending"}, {"x": 184, "y": 393, "type": "bifurcation"}, {"x": 184, "y": 396, "type": "bifurcation"}, {"x": 184, "y": 398, "type": "bifurcation"}, {"x": 185, "y": 87, "type": "bifurcation"}, {"x": 186, "y": 93, "type": "ending"}, {"x": 186, "y": 94, "type": "bifurcation"}, {"x": 186, "y": 375, "type": "ending"}, {"x": 186, "y": 398, "type": "ending"}, {"x": 187, "y": 338, "type": "bifurcation"}, {"x": 188, "y": 98, "type": "ending"}, {"x": 188, "y": 104, "type": "ending"}, {"x": 188, "y": 336, "type": "bifurcation"}, {"x": 188, "y": 424, "type": "ending"}, {"x": 189, "y": 325, "type": "bifurcation"}, {"x": 189, "y": 328, "type": "bifurcation"}, {"x": 191, "y": 81, "type": "ending"}, {"x": 191, "y": 89, "type": "bifurcation"}, {"x": 191, "y": 325, "type": "ending"}, {"x": 192, "y": 222, "type": "bifurcation"}, {"x": 192, "y": 374, "type": "ending"}, {"x": 192, "y": 403, "type": "bifurcation"}, {"x": 194, "y": 81, "type": "ending"}, {"x": 194, "y": 82, "type": "bifurcation"}, {"x": 194, "y": 391, "type": "bifurcation"}, {"x": 194, "y": 396, "type": "bifurcation"}, {"x": 194, "y": 424, "type": "ending"}, {"x": 196, "y": 88, "type": "ending"}, {"x": 196, "y": 314, "type": "bifurcation"}, {"x": 196, "y": 380, "type": "bifurcation"}, {"x": 196, "y": 381, "type": "ending"}, {"x": 197, "y": 327, "type": "ending"}, {"x": 197, "y": 328, "type": "ending"}, {"x": 197, "y": 395, "type": "bifurcation"}, {"x": 198, "y": 382, "type": "ending"}, {"x": 199, "y": 316, "type": "bifurcation"}, {"x": 200, "y": 424, "type": "ending"}, {"x": 201, "y": 314, "type": "bifurcation"}, {"x": 201, "y": 328, "type": "ending"}, {"x": 202, "y": 384, "type": "ending"}, {"x": 202, "y": 411, "type": "bifurcation"}, {"x": 204, "y": 91, "type": "bifurcation"}, {"x": 204, "y": 95, "type": "ending"}, {"x": 204, "y": 259, "type": "ending"}, {"x": 205, "y": 101, "type": "bifurcation"}, {"x": 205, "y": 416, "type": "bifurcation"}, {"x": 206, "y": 82, "type": "ending"}, {"x": 206, "y": 254, "type": "ending"}, {"x": 206, "y": 414, "type": "ending"}, {"x": 207, "y": 424, "type": "ending"}, {"x": 208, "y": 102, "type": "ending"}, {"x": 208, "y": 382, "type": "ending"}, {"x": 208, "y": 423, "type": "ending"}, {"x": 209, "y": 95, "type": "bifurcation"}, {"x": 210, "y": 97, "type": "ending"}, {"x": 210, "y": 370, "type": "bifurcation"}, {"x": 210, "y": 373, "type": "ending"}, {"x": 211, "y": 371, "type": "bifurcation"}, {"x": 212, "y": 367, "type": "bifurcation"}, {"x": 213, "y": 265, "type": "bifurcation"}, {"x": 213, "y": 387, "type": "bifurcation"}, {"x": 214, "y": 424, "type": "ending"}, {"x": 215, "y": 267, "type": "bifurcation"}, {"x": 216, "y": 263, "type": "bifurcation"}, {"x": 216, "y": 300, "type": "ending"}, {"x": 217, "y": 95, "type": "ending"}, {"x": 217, "y": 96, "type": "ending"}, {"x": 217, "y": 418, "type": "bifurcation"}, {"x": 219, "y": 384, "type": "ending"}, {"x": 220, "y": 383, "type": "ending"}, {"x": 220, "y": 384, "type": "bifurcation"}, {"x": 220, "y": 387, "type": "ending"}, {"x": 221, "y": 187, "type": "bifurcation"}, {"x": 221, "y": 385, "type": "bifurcation"}, {"x": 221, "y": 401, "type": "bifurcation"}, {"x": 222, "y": 189, "type": "ending"}, {"x": 222, "y": 267, "type": "bifurcation"}, {"x": 222, "y": 409, "type": "bifurcation"}, {"x": 224, "y": 80, "type": "ending"}, {"x": 224, "y": 150, "type": "ending"}, {"x": 224, "y": 229, "type": "bifurcation"}, {"x": 224, "y": 232, "type": "ending"}, {"x": 224, "y": 234, "type": "ending"}, {"x": 224, "y": 251, "type": "ending"}, {"x": 224, "y": 393, "type": "ending"}, {"x": 224, "y": 420, "type": "ending"}, {"x": 225, "y": 87, "type": "bifurcation"}, {"x": 225, "y": 249, "type": "bifurcation"}, {"x": 225, "y": 424, "type": "ending"}, {"x": 226, "y": 84, "type": "ending"}, {"x": 228, "y": 412, "type": "bifurcation"}, {"x": 228, "y": 420, "type": "bifurcation"}, {"x": 228, "y": 422, "type": "bifurcation"}, {"x": 229, "y": 421, "type": "bifurcation"}, {"x": 230, "y": 221, "type": "ending"}, {"x": 230, "y": 251, "type": "bifurcation"}, {"x": 230, "y": 412, "type": "ending"}, {"x": 230, "y": 424, "type": "ending"}, {"x": 231, "y": 239, "type": "bifurcation"}, {"x": 232, "y": 115, "type": "bifurcation"}, {"x": 233, "y": 230, "type": "ending"}, {"x": 234, "y": 103, "type": "bifurcation"}, {"x": 234, "y": 220, "type": "ending"}, {"x": 234, "y": 230, "type": "bifurcation"}, {"x": 234, "y": 244, "type": "bifurcation"}, {"x": 234, "y": 387, "type": "bifurcation"}, {"x": 235, "y": 235, "type": "bifurcation"}, {"x": 236, "y": 80, "type": "ending"}, {"x": 236, "y": 193, "type": "ending"}, {"x": 236, "y": 233, "type": "bifurcation"}, {"x": 236, "y": 237, "type": "ending"}, {"x": 236, "y": 398, "type": "ending"}, {"x": 237, "y": 156, "type": "ending"}, {"x": 237, "y": 223, "type": "ending"}, {"x": 237, "y": 410, "type": "bifurcation"}, {"x": 238, "y": 102, "type": "ending"}, {"x": 238, "y": 248, "type": "ending"}, {"x": 238, "y": 424, "type": "ending"}, {"x": 239, "y": 383, "type": "ending"}, {"x": 240, "y": 142, "type": "ending"}, {"x": 240, "y": 378, "type": "ending"}, {"x": 241, "y": 239, "type": "bifurcation"}, {"x": 242, "y": 80, "type": "ending"}, {"x": 242, "y": 85, "type": "bifurcation"}, {"x": 242, "y": 118, "type": "ending"}, {"x": 242, "y": 154, "type": "ending"}, {"x": 242, "y": 241, "type": "ending"}, {"x": 243, "y": 121, "type": "bifurcation"}, {"x": 243, "y": 400, "type": "ending"}, {"x": 244, "y": 123, "type": "ending"}, {"x": 244, "y": 145, "type": "ending"}, {"x": 244, "y": 248, "type": "ending"}, {"x": 245, "y": 119, "type": "bifurcation"}, {"x": 246, "y": 408, "type": "ending"}, {"x": 246, "y": 413, "type": "ending"}, {"x": 246, "y": 425, "type": "ending"}, {"x": 247, "y": 118, "type": "bifurcation"}, {"x": 248, "y": 105, "type": "bifurcation"}, {"x": 248, "y": 266, "type": "bifurcation"}, {"x": 248, "y": 380, "type": "ending"}, {"x": 248, "y": 418, "type": "bifurcation"}, {"x": 248, "y": 421, "type": "bifurcation"}, {"x": 249, "y": 80, "type": "ending"}, {"x": 250, "y": 118, "type": "ending"}, {"x": 250, "y": 126, "type": "bifurcation"}, {"x": 250, "y": 423, "type": "ending"}, {"x": 251, "y": 353, "type": "bifurcation"}, {"x": 252, "y": 87, "type": "ending"}, {"x": 252, "y": 430, "type": "ending"}, {"x": 253, "y": 310, "type": "bifurcation"}, {"x": 254, "y": 100, "type": "bifurcation"}, {"x": 254, "y": 111, "type": "bifurcation"}, {"x": 254, "y": 248, "type": "ending"}, {"x": 255, "y": 80, "type": "ending"}, {"x": 255, "y": 355, "type": "bifurcation"}, {"x": 255, "y": 404, "type": "bifurcation"}, {"x": 257, "y": 426, "type": "bifurcation"}, {"x": 258, "y": 237, "type": "bifurcation"}, {"x": 260, "y": 222, "type": "bifurcation"}, {"x": 260, "y": 226, "type": "ending"}, {"x": 260, "y": 396, "type": "bifurcation"}, {"x": 260, "y": 397, "type": "ending"}, {"x": 261, "y": 115, "type": "bifurcation"}, {"x": 261, "y": 412, "type": "bifurcation"}, {"x": 262, "y": 220, "type": "bifurcation"}, {"x": 262, "y": 433, "type": "ending"}, {"x": 263, "y": 88, "type": "bifurcation"}, {"x": 263, "y": 100, "type": "bifurcation"}, {"x": 263, "y": 102, "type": "bifurcation"}, {"x": 265, "y": 89, "type": "bifurcation"}, {"x": 265, "y": 117, "type": "bifurcation"}, {"x": 265, "y": 407, "type": "ending"}, {"x": 266, "y": 109, "type": "ending"}, {"x": 266, "y": 405, "type": "bifurcation"}, {"x": 266, "y": 412, "type": "ending"}, {"x": 267, "y": 75, "type": "ending"}, {"x": 267, "y": 87, "type": "bifurcation"}, {"x": 268, "y": 106, "type": "bifurcation"}, {"x": 268, "y": 118, "type": "ending"}, {"x": 269, "y": 75, "type": "ending"}, {"x": 269, "y": 106, "type": "bifurcation"}, {"x": 270, "y": 90, "type": "ending"}, {"x": 270, "y": 333, "type": "ending"}, {"x": 270, "y": 410, "type": "ending"}, {"x": 271, "y": 105, "type": "bifurcation"}, {"x": 272, "y": 104, "type": "bifurcation"}, {"x": 272, "y": 106, "type": "bifurcation"}, {"x": 272, "y": 110, "type": "bifurcation"}, {"x": 272, "y": 329, "type": "bifurcation"}, {"x": 272, "y": 330, "type": "bifurcation"}, {"x": 273, "y": 105, "type": "bifurcation"}, {"x": 273, "y": 121, "type": "bifurcation"}, {"x": 273, "y": 388, "type": "bifurcation"}, {"x": 274, "y": 327, "type": "ending"}, {"x": 274, "y": 328, "type": "bifurcation"}, {"x": 275, "y": 99, "type": "bifurcation"}, {"x": 275, "y": 429, "type": "bifurcation"}, {"x": 276, "y": 101, "type": "ending"}, {"x": 276, "y": 391, "type": "bifurcation"}, {"x": 276, "y": 396, "type": "ending"}, {"x": 276, "y": 432, "type": "ending"}, {"x": 277, "y": 416, "type": "bifurcation"}, {"x": 279, "y": 119, "type": "bifurcation"}, {"x": 279, "y": 298, "type": "bifurcation"}, {"x": 280, "y": 88, "type": "ending"}, {"x": 280, "y": 90, "type": "ending"}, {"x": 280, "y": 102, "type": "ending"}, {"x": 280, "y": 108, "type": "ending"}, {"x": 280, "y": 408, "type": "bifurcation"}, {"x": 281, "y": 114, "type": "bifurcation"}, {"x": 282, "y": 88, "type": "ending"}, {"x": 282, "y": 90, "type": "ending"}, {"x": 282, "y": 122, "type": "ending"}, {"x": 282, "y": 420, "type": "ending"}, {"x": 283, "y": 235, "type": "bifurcation"}, {"x": 283, "y": 306, "type": "bifurcation"}, {"x": 284, "y": 75, "type": "ending"}, {"x": 284, "y": 111, "type": "bifurcation"}, {"x": 285, "y": 110, "type": "bifurcation"}, {"x": 285, "y": 112, "type": "bifurcation"}, {"x": 285, "y": 305, "type": "bifurcation"}, {"x": 286, "y": 111, "type": "bifurcation"}, {"x": 286, "y": 122, "type": "ending"}, {"x": 286, "y": 426, "type": "ending"}, {"x": 286, "y": 430, "type": "ending"}, {"x": 287, "y": 112, "type": "bifurcation"}, {"x": 287, "y": 307, "type": "bifurcation"}, {"x": 288, "y": 248, "type": "ending"}, {"x": 289, "y": 105, "type": "bifurcation"}, {"x": 289, "y": 122, "type": "bifurcation"}, {"x": 290, "y": 304, "type": "bifurcation"}, {"x": 290, "y": 305, "type": "bifurcation"}, {"x": 291, "y": 83, "type": "bifurcation"}, {"x": 292, "y": 85, "type": "ending"}, {"x": 292, "y": 157, "type": "ending"}, {"x": 292, "y": 158, "type": "bifurcation"}, {"x": 292, "y": 314, "type": "bifurcation"}, {"x": 293, "y": 77, "type": "bifurcation"}, {"x": 293, "y": 98, "type": "bifurcation"}, {"x": 294, "y": 79, "type": "ending"}, {"x": 295, "y": 383, "type": "bifurcation"}, {"x": 296, "y": 90, "type": "ending"}, {"x": 296, "y": 98, "type": "ending"}, {"x": 296, "y": 124, "type": "ending"}, {"x": 296, "y": 393, "type": "ending"}, {"x": 297, "y": 141, "type": "bifurcation"}, {"x": 297, "y": 391, "type": "bifurcation"}, {"x": 297, "y": 429, "type": "bifurcation"}, {"x": 298, "y": 103, "type": "ending"}, {"x": 298, "y": 131, "type": "ending"}, {"x": 299, "y": 72, "type": "bifurcation"}, {"x": 299, "y": 80, "type": "ending"}, {"x": 300, "y": 394, "type": "ending"}, {"x": 301, "y": 70, "type": "ending"}, {"x": 303, "y": 299, "type": "bifurcation"}, {"x": 303, "y": 433, "type": "ending"}, {"x": 304, "y": 133, "type": "bifurcation"}, {"x": 305, "y": 243, "type": "bifurcation"}, {"x": 305, "y": 323, "type": "bifurcation"}, {"x": 306, "y": 135, "type": "ending"}, {"x": 306, "y": 248, "type": "ending"}, {"x": 308, "y": 322, "type": "ending"}, {"x": 309, "y": 303, "type": "bifurcation"}, {"x": 310, "y": 74, "type": "bifurcation"}, {"x": 310, "y": 93, "type": "bifurcation"}, {"x": 310, "y": 305, "type": "ending"}, {"x": 310, "y": 312, "type": "ending"}, {"x": 310, "y": 328, "type": "ending"}, {"x": 310, "y": 338, "type": "ending"}, {"x": 310, "y": 363, "type": "ending"}, {"x": 310, "y": 386, "type": "bifurcation"}, {"x": 311, "y": 89, "type": "bifurcation"}, {"x": 311, "y": 433, "type": "ending"}, {"x": 312, "y": 70, "type": "ending"}, {"x": 313, "y": 161, "type": "bifurcation"}, {"x": 314, "y": 86, "type": "bifurcation"}, {"x": 314, "y": 163, "type": "ending"}, {"x": 314, "y": 172, "type": "bifurcation"}, {"x": 314, "y": 190, "type": "ending"}, {"x": 315, "y": 87, "type": "bifurcation"}, {"x": 316, "y": 89, "type": "ending"}, {"x": 316, "y": 306, "type": "ending"}, {"x": 317, "y": 434, "type": "ending"}, {"x": 318, "y": 321, "type": "ending"}, {"x": 319, "y": 155, "type": "bifurcation"}, {"x": 319, "y": 306, "type": "ending"}, {"x": 319, "y": 319, "type": "bifurcation"}, {"x": 320, "y": 126, "type": "ending"}, {"x": 320, "y": 157, "type": "ending"}, {"x": 320, "y": 306, "type": "bifurcation"}, {"x": 320, "y": 307, "type": "ending"}, {"x": 320, "y": 312, "type": "ending"}, {"x": 320, "y": 321, "type": "ending"}, {"x": 321, "y": 66, "type": "ending"}, {"x": 321, "y": 315, "type": "bifurcation"}, {"x": 322, "y": 68, "type": "bifurcation"}, {"x": 322, "y": 107, "type": "bifurcation"}, {"x": 322, "y": 127, "type": "ending"}, {"x": 323, "y": 103, "type": "bifurcation"}, {"x": 323, "y": 108, "type": "ending"}, {"x": 324, "y": 68, "type": "ending"}, {"x": 324, "y": 213, "type": "ending"}, {"x": 325, "y": 302, "type": "bifurcation"}, {"x": 325, "y": 309, "type": "bifurcation"}, {"x": 325, "y": 429, "type": "bifurcation"}, {"x": 326, "y": 111, "type": "ending"}, {"x": 326, "y": 311, "type": "ending"}, {"x": 326, "y": 434, "type": "ending"}, {"x": 327, "y": 133, "type": "bifurcation"}, {"x": 328, "y": 135, "type": "ending"}, {"x": 329, "y": 66, "type": "ending"}, {"x": 329, "y": 101, "type": "bifurcation"}, {"x": 331, "y": 115, "type": "ending"}, {"x": 331, "y": 128, "type": "bifurcation"}, {"x": 331, "y": 270, "type": "bifurcation"}, {"x": 331, "y": 358, "type": "bifurcation"}, {"x": 332, "y": 110, "type": "bifurcation"}, {"x": 332, "y": 113, "type": "bifurcation"}, {"x": 333, "y": 89, "type": "bifurcation"}, {"x": 334, "y": 68, "type": "ending"}, {"x": 334, "y": 94, "type": "ending"}, {"x": 334, "y": 102, "type": "ending"}, {"x": 334, "y": 164, "type": "bifurcation"}, {"x": 336, "y": 107, "type": "bifurcation"}, {"x": 336, "y": 434, "type": "ending"}, {"x": 337, "y": 102, "type": "bifurcation"}, {"x": 338, "y": 78, "type": "ending"}, {"x": 338, "y": 94, "type": "ending"}, {"x": 338, "y": 281, "type": "bifurcation"}, {"x": 338, "y": 378, "type": "ending"}, {"x": 340, "y": 97, "type": "bifurcation"}, {"x": 340, "y": 129, "type": "ending"}, {"x": 340, "y": 424, "type": "ending"}, {"x": 341, "y": 421, "type": "bifurcation"}, {"x": 342, "y": 66, "type": "ending"}, {"x": 342, "y": 67, "type": "ending"}, {"x": 343, "y": 343, "type": "bifurcation"}, {"x": 343, "y": 383, "type": "bifurcation"}, {"x": 345, "y": 425, "type": "bifurcation"}, {"x": 346, "y": 80, "type": "ending"}, {"x": 346, "y": 102, "type": "ending"}, {"x": 346, "y": 196, "type": "ending"}, {"x": 346, "y": 342, "type": "ending"}, {"x": 346, "y": 382, "type": "ending"}, {"x": 347, "y": 66, "type": "ending"}, {"x": 348, "y": 79, "type": "ending"}, {"x": 348, "y": 106, "type": "bifurcation"}, {"x": 348, "y": 436, "type": "ending"}, {"x": 349, "y": 108, "type": "bifurcation"}, {"x": 350, "y": 120, "type": "ending"}, {"x": 352, "y": 108, "type": "ending"}, {"x": 352, "y": 136, "type": "ending"}, {"x": 354, "y": 133, "type": "bifurcation"}, {"x": 354, "y": 163, "type": "ending"}, {"x": 354, "y": 260, "type": "ending"}, {"x": 354, "y": 262, "type": "bifurcation"}, {"x": 354, "y": 421, "type": "ending"}, {"x": 354, "y": 442, "type": "ending"}, {"x": 355, "y": 214, "type": "bifurcation"}, {"x": 356, "y": 263, "type": "bifurcation"}, {"x": 356, "y": 385, "type": "bifurcation"}, {"x": 357, "y": 103, "type": "ending"}, {"x": 357, "y": 385, "type": "bifurcation"}, {"x": 357, "y": 397, "type": "bifurcation"}, {"x": 358, "y": 63, "type": "ending"}, {"x": 358, "y": 130, "type": "ending"}, {"x": 359, "y": 107, "type": "bifurcation"}, {"x": 360, "y": 63, "type": "ending"}, {"x": 361, "y": 133, "type": "ending"}, {"x": 361, "y": 447, "type": "ending"}, {"x": 362, "y": 70, "type": "ending"}, {"x": 362, "y": 102, "type": "bifurcation"}, {"x": 362, "y": 136, "type": "ending"}, {"x": 362, "y": 140, "type": "ending"}, {"x": 362, "y": 237, "type": "bifurcation"}, {"x": 363, "y": 75, "type": "ending"}, {"x": 363, "y": 143, "type": "bifurcation"}, {"x": 363, "y": 434, "type": "bifurcation"}, {"x": 364, "y": 86, "type": "bifurcation"}, {"x": 364, "y": 105, "type": "ending"}, {"x": 364, "y": 126, "type": "bifurcation"}, {"x": 366, "y": 58, "type": "ending"}, {"x": 366, "y": 108, "type": "ending"}, {"x": 367, "y": 59, "type": "bifurcation"}, {"x": 367, "y": 137, "type": "bifurcation"}, {"x": 368, "y": 139, "type": "ending"}, {"x": 368, "y": 190, "type": "ending"}, {"x": 368, "y": 409, "type": "bifurcation"}, {"x": 368, "y": 446, "type": "ending"}, {"x": 369, "y": 56, "type": "ending"}, {"x": 369, "y": 120, "type": "ending"}, {"x": 369, "y": 179, "type": "bifurcation"}, {"x": 370, "y": 72, "type": "bifurcation"}, {"x": 370, "y": 181, "type": "ending"}, {"x": 370, "y": 410, "type": "ending"}, {"x": 370, "y": 444, "type": "bifurcation"}, {"x": 370, "y": 445, "type": "ending"}, {"x": 371, "y": 72, "type": "ending"}, {"x": 372, "y": 84, "type": "ending"}, {"x": 373, "y": 120, "type": "ending"}, {"x": 374, "y": 120, "type": "bifurcation"}, {"x": 374, "y": 132, "type": "bifurcation"}, {"x": 374, "y": 395, "type": "ending"}, {"x": 375, "y": 121, "type": "bifurcation"}, {"x": 375, "y": 126, "type": "ending"}, {"x": 375, "y": 393, "type": "bifurcation"}, {"x": 375, "y": 427, "type": "bifurcation"}, {"x": 375, "y": 429, "type": "bifurcation"}, {"x": 376, "y": 55, "type": "ending"}, {"x": 376, "y": 86, "type": "ending"}, {"x": 376, "y": 118, "type": "ending"}, {"x": 376, "y": 123, "type": "bifurcation"}, {"x": 376, "y": 131, "type": "ending"}, {"x": 376, "y": 423, "type": "bifurcation"}, {"x": 377, "y": 95, "type": "ending"}, {"x": 377, "y": 425, "type": "bifurcation"}, {"x": 377, "y": 447, "type": "ending"}, {"x": 378, "y": 70, "type": "bifurcation"}, {"x": 378, "y": 86, "type": "bifurcation"}, {"x": 378, "y": 145, "type": "ending"}, {"x": 378, "y": 396, "type": "bifurcation"}, {"x": 378, "y": 397, "type": "bifurcation"}, {"x": 378, "y": 426, "type": "bifurcation"}, {"x": 379, "y": 370, "type": "bifurcation"}, {"x": 379, "y": 379, "type": "bifurcation"}, {"x": 379, "y": 426, "type": "ending"}, {"x": 380, "y": 70, "type": "ending"}, {"x": 380, "y": 106, "type": "bifurcation"}, {"x": 380, "y": 123, "type": "bifurcation"}, {"x": 380, "y": 399, "type": "ending"}, {"x": 381, "y": 118, "type": "bifurcation"}, {"x": 382, "y": 394, "type": "ending"}, {"x": 382, "y": 446, "type": "ending"}, {"x": 382, "y": 447, "type": "ending"}, {"x": 384, "y": 55, "type": "ending"}, {"x": 384, "y": 70, "type": "ending"}, {"x": 384, "y": 72, "type": "ending"}, {"x": 384, "y": 111, "type": "ending"}, {"x": 385, "y": 109, "type": "bifurcation"}, {"x": 385, "y": 130, "type": "bifurcation"}, {"x": 385, "y": 203, "type": "ending"}, {"x": 385, "y": 269, "type": "ending"}, {"x": 386, "y": 95, "type": "bifurcation"}, {"x": 386, "y": 102, "type": "ending"}, {"x": 386, "y": 379, "type": "ending"}, {"x": 386, "y": 399, "type": "ending"}, {"x": 386, "y": 412, "type": "ending"}, {"x": 387, "y": 70, "type": "bifurcation"}, {"x": 387, "y": 72, "type": "bifurcation"}, {"x": 387, "y": 423, "type": "bifurcation"}, {"x": 388, "y": 74, "type": "bifurcation"}, {"x": 388, "y": 111, "type": "bifurcation"}, {"x": 388, "y": 130, "type": "ending"}, {"x": 388, "y": 395, "type": "bifurcation"}, {"x": 388, "y": 447, "type": "ending"}, {"x": 389, "y": 375, "type": "bifurcation"}, {"x": 389, "y": 403, "type": "bifurcation"}, {"x": 389, "y": 419, "type": "bifurcation"}, {"x": 390, "y": 77, "type": "ending"}, {"x": 390, "y": 112, "type": "ending"}, {"x": 390, "y": 148, "type": "ending"}, {"x": 390, "y": 405, "type": "ending"}, {"x": 391, "y": 425, "type": "bifurcation"}, {"x": 392, "y": 55, "type": "ending"}, {"x": 392, "y": 148, "type": "bifurcation"}, {"x": 393, "y": 126, "type": "bifurcation"}, {"x": 393, "y": 221, "type": "bifurcation"}, {"x": 393, "y": 413, "type": "bifurcation"}, {"x": 394, "y": 55, "type": "ending"}, {"x": 394, "y": 56, "type": "bifurcation"}, {"x": 394, "y": 72, "type": "ending"}, {"x": 394, "y": 415, "type": "ending"}, {"x": 394, "y": 447, "type": "ending"}, {"x": 395, "y": 57, "type": "bifurcation"}, {"x": 395, "y": 92, "type": "ending"}, {"x": 395, "y": 104, "type": "ending"}, {"x": 395, "y": 125, "type": "bifurcation"}, {"x": 395, "y": 133, "type": "bifurcation"}, {"x": 395, "y": 161, "type": "ending"}, {"x": 396, "y": 55, "type": "ending"}, {"x": 396, "y": 104, "type": "bifurcation"}, {"x": 396, "y": 430, "type": "ending"}, {"x": 397, "y": 107, "type": "bifurcation"}, {"x": 398, "y": 93, "type": "ending"}, {"x": 398, "y": 119, "type": "ending"}, {"x": 398, "y": 126, "type": "ending"}, {"x": 398, "y": 134, "type": "ending"}, {"x": 398, "y": 403, "type": "bifurcation"}, {"x": 398, "y": 430, "type": "bifurcation"}, {"x": 399, "y": 91, "type": "bifurcation"}, {"x": 400, "y": 93, "type": "ending"}, {"x": 400, "y": 108, "type": "ending"}, {"x": 400, "y": 405, "type": "ending"}, {"x": 401, "y": 76, "type": "ending"}, {"x": 401, "y": 409, "type": "ending"}, {"x": 402, "y": 447, "type": "ending"}, {"x": 403, "y": 100, "type": "ending"}, {"x": 403, "y": 114, "type": "ending"}, {"x": 404, "y": 114, "type": "bifurcation"}, {"x": 404, "y": 240, "type": "ending"}, {"x": 404, "y": 444, "type": "ending"}, {"x": 405, "y": 395, "type": "ending"}, {"x": 406, "y": 102, "type": "bifurcation"}, {"x": 406, "y": 207, "type": "bifurcation"}, {"x": 406, "y": 295, "type": "bifurcation"}, {"x": 406, "y": 298, "type": "bifurcation"}, {"x": 406, "y": 414, "type": "ending"}, {"x": 406, "y": 420, "type": "ending"}, {"x": 407, "y": 53, "type": "ending"}, {"x": 407, "y": 109, "type": "bifurcation"}, {"x": 407, "y": 127, "type": "bifurcation"}, {"x": 407, "y": 204, "type": "bifurcation"}, {"x": 407, "y": 420, "type": "ending"}, {"x": 408, "y": 76, "type": "bifurcation"}, {"x": 408, "y": 130, "type": "ending"}, {"x": 408, "y": 209, "type": "ending"}, {"x": 408, "y": 301, "type": "ending"}, {"x": 408, "y": 406, "type": "ending"}, {"x": 409, "y": 75, "type": "bifurcation"}, {"x": 409, "y": 92, "type": "bifurcation"}, {"x": 409, "y": 399, "type": "bifurcation"}, {"x": 409, "y": 413, "type": "bifurcation"}, {"x": 409, "y": 447, "type": "ending"}, {"x": 410, "y": 73, "type": "bifurcation"}, {"x": 410, "y": 113, "type": "ending"}, {"x": 410, "y": 204, "type": "ending"}, {"x": 410, "y": 240, "type": "ending"}, {"x": 410, "y": 268, "type": "ending"}, {"x": 410, "y": 412, "type": "bifurcation"}, {"x": 410, "y": 413, "type": "bifurcation"}, {"x": 410, "y": 443, "type": "bifurcation"}, {"x": 411, "y": 72, "type": "bifurcation"}, {"x": 411, "y": 159, "type": "bifurcation"}, {"x": 412, "y": 69, "type": "bifurcation"}, {"x": 412, "y": 92, "type": "ending"}, {"x": 412, "y": 257, "type": "ending"}, {"x": 413, "y": 160, "type": "bifurcation"}, {"x": 414, "y": 70, "type": "ending"}, {"x": 414, "y": 119, "type": "bifurcation"}, {"x": 414, "y": 122, "type": "bifurcation"}, {"x": 414, "y": 171, "type": "ending"}, {"x": 414, "y": 447, "type": "ending"}, {"x": 415, "y": 86, "type": "ending"}, {"x": 415, "y": 113, "type": "ending"}, {"x": 415, "y": 385, "type": "bifurcation"}, {"x": 416, "y": 94, "type": "ending"}, {"x": 416, "y": 118, "type": "bifurcation"}, {"x": 416, "y": 141, "type": "bifurcation"}, {"x": 416, "y": 160, "type": "ending"}, {"x": 416, "y": 352, "type": "ending"}, {"x": 416, "y": 446, "type": "ending"}, {"x": 416, "y": 447, "type": "ending"}, {"x": 417, "y": 53, "type": "ending"}, {"x": 417, "y": 118, "type": "bifurcation"}, {"x": 417, "y": 313, "type": "ending"}, {"x": 417, "y": 408, "type": "ending"}, {"x": 418, "y": 110, "type": "bifurcation"}, {"x": 418, "y": 119, "type": "bifurcation"}, {"x": 418, "y": 279, "type": "ending"}, {"x": 419, "y": 111, "type": "bifurcation"}, {"x": 419, "y": 385, "type": "bifurcation"}, {"x": 419, "y": 396, "type": "ending"}, {"x": 420, "y": 59, "type": "ending"}, {"x": 420, "y": 192, "type": "bifurcation"}, {"x": 420, "y": 379, "type": "ending"}, {"x": 420, "y": 382, "type": "bifurcation"}, {"x": 420, "y": 405, "type": "bifurcation"}, {"x": 420, "y": 411, "type": "bifurcation"}, {"x": 420, "y": 413, "type": "bifurcation"}, {"x": 421, "y": 382, "type": "ending"}, {"x": 421, "y": 390, "type": "bifurcation"}, {"x": 422, "y": 66, "type": "bifurcation"}, {"x": 422, "y": 150, "type": "ending"}, {"x": 422, "y": 365, "type": "ending"}, {"x": 422, "y": 396, "type": "ending"}, {"x": 422, "y": 403, "type": "bifurcation"}, {"x": 422, "y": 448, "type": "ending"}, {"x": 423, "y": 65, "type": "bifurcation"}, {"x": 423, "y": 332, "type": "ending"}, {"x": 423, "y": 355, "type": "bifurcation"}, {"x": 423, "y": 363, "type": "bifurcation"}, {"x": 423, "y": 399, "type": "bifurcation"}, {"x": 424, "y": 76, "type": "ending"}, {"x": 424, "y": 90, "type": "bifurcation"}, {"x": 424, "y": 91, "type": "ending"}, {"x": 424, "y": 262, "type": "ending"}, {"x": 424, "y": 388, "type": "ending"}, {"x": 424, "y": 396, "type": "ending"}, {"x": 424, "y": 409, "type": "bifurcation"}, {"x": 425, "y": 53, "type": "ending"}, {"x": 425, "y": 90, "type": "ending"}, {"x": 425, "y": 117, "type": "bifurcation"}, {"x": 425, "y": 150, "type": "bifurcation"}, {"x": 425, "y": 161, "type": "bifurcation"}, {"x": 425, "y": 232, "type": "ending"}, {"x": 426, "y": 66, "type": "ending"}, {"x": 426, "y": 98, "type": "ending"}, {"x": 426, "y": 322, "type": "ending"}, {"x": 426, "y": 345, "type": "ending"}, {"x": 426, "y": 381, "type": "ending"}, {"x": 426, "y": 410, "type": "bifurcation"}, {"x": 427, "y": 366, "type": "bifurcation"}, {"x": 427, "y": 409, "type": "bifurcation"}, {"x": 427, "y": 411, "type": "bifurcation"}, {"x": 428, "y": 193, "type": "ending"}, {"x": 428, "y": 231, "type": "bifurcation"}, {"x": 428, "y": 311, "type": "bifurcation"}, {"x": 428, "y": 322, "type": "bifurcation"}, {"x": 428, "y": 325, "type": "ending"}, {"x": 428, "y": 379, "type": "bifurcation"}, {"x": 428, "y": 385, "type": "ending"}, {"x": 428, "y": 396, "type": "ending"}, {"x": 428, "y": 410, "type": "bifurcation"}, {"x": 428, "y": 430, "type": "ending"}, {"x": 429, "y": 323, "type": "bifurcation"}, {"x": 429, "y": 378, "type": "bifurcation"}, {"x": 430, "y": 56, "type": "ending"}, {"x": 430, "y": 89, "type": "ending"}, {"x": 430, "y": 108, "type": "ending"}, {"x": 430, "y": 260, "type": "bifurcation"}, {"x": 430, "y": 396, "type": "bifurcation"}, {"x": 432, "y": 149, "type": "ending"}, {"x": 432, "y": 150, "type": "ending"}, {"x": 432, "y": 341, "type": "bifurcation"}, {"x": 432, "y": 348, "type": "bifurcation"}, {"x": 432, "y": 378, "type": "ending"}, {"x": 432, "y": 424, "type": "ending"}, {"x": 432, "y": 449, "type": "ending"}, {"x": 433, "y": 56, "type": "bifurcation"}, {"x": 433, "y": 62, "type": "bifurcation"}, {"x": 433, "y": 78, "type": "ending"}, {"x": 434, "y": 53, "type": "ending"}, {"x": 434, "y": 55, "type": "bifurcation"}, {"x": 434, "y": 57, "type": "bifurcation"}, {"x": 434, "y": 93, "type": "bifurcation"}, {"x": 434, "y": 125, "type": "bifurcation"}, {"x": 434, "y": 162, "type": "ending"}, {"x": 434, "y": 325, "type": "bifurcation"}, {"x": 434, "y": 343, "type": "ending"}, {"x": 434, "y": 347, "type": "ending"}, {"x": 434, "y": 386, "type": "ending"}, {"x": 434, "y": 421, "type": "ending"}, {"x": 435, "y": 56, "type": "bifurcation"}, {"x": 435, "y": 257, "type": "bifurcation"}, {"x": 436, "y": 73, "type": "bifurcation"}, {"x": 436, "y": 74, "type": "bifurcation"}, {"x": 436, "y": 122, "type": "bifurcation"}, {"x": 436, "y": 131, "type": "bifurcation"}, {"x": 436, "y": 148, "type": "ending"}, {"x": 436, "y": 298, "type": "bifurcation"}, {"x": 436, "y": 419, "type": "bifurcation"}, {"x": 437, "y": 156, "type": "ending"}, {"x": 437, "y": 195, "type": "bifurcation"}, {"x": 437, "y": 238, "type": "bifurcation"}, {"x": 437, "y": 268, "type": "bifurcation"}, {"x": 437, "y": 384, "type": "ending"}, {"x": 437, "y": 422, "type": "ending"}, {"x": 438, "y": 127, "type": "bifurcation"}, {"x": 438, "y": 205, "type": "bifurcation"}, {"x": 438, "y": 206, "type": "bifurcation"}, {"x": 438, "y": 260, "type": "bifurcation"}, {"x": 438, "y": 302, "type": "bifurcation"}, {"x": 438, "y": 371, "type": "ending"}, {"x": 439, "y": 53, "type": "ending"}, {"x": 439, "y": 103, "type": "bifurcation"}, {"x": 439, "y": 125, "type": "bifurcation"}, {"x": 439, "y": 129, "type": "bifurcation"}, {"x": 439, "y": 245, "type": "bifurcation"}, {"x": 439, "y": 259, "type": "bifurcation"}, {"x": 440, "y": 269, "type": "bifurcation"}, {"x": 440, "y": 302, "type": "ending"}, {"x": 440, "y": 349, "type": "ending"}, {"x": 440, "y": 384, "type": "bifurcation"}, {"x": 441, "y": 347, "type": "bifurcation"}, {"x": 442, "y": 93, "type": "ending"}, {"x": 442, "y": 107, "type": "bifurcation"}, {"x": 442, "y": 157, "type": "bifurcation"}, {"x": 442, "y": 320, "type": "ending"}, {"x": 442, "y": 327, "type": "ending"}, {"x": 442, "y": 438, "type": "ending"}, {"x": 443, "y": 338, "type": "bifurcation"}, {"x": 444, "y": 108, "type": "ending"}, {"x": 444, "y": 138, "type": "bifurcation"}, {"x": 444, "y": 416, "type": "ending"}, {"x": 446, "y": 63, "type": "ending"}, {"x": 446, "y": 139, "type": "ending"}, {"x": 446, "y": 194, "type": "ending"}, {"x": 446, "y": 278, "type": "ending"}, {"x": 446, "y": 284, "type": "ending"}, {"x": 446, "y": 288, "type": "ending"}, {"x": 446, "y": 313, "type": "bifurcation"}, {"x": 446, "y": 367, "type": "bifurcation"}, {"x": 446, "y": 396, "type": "ending"}, {"x": 446, "y": 398, "type": "ending"}, {"x": 446, "y": 449, "type": "ending"}, {"x": 447, "y": 142, "type": "ending"}, {"x": 447, "y": 393, "type": "bifurcation"}, {"x": 447, "y": 416, "type": "bifurcation"}, {"x": 448, "y": 151, "type": "ending"}, {"x": 448, "y": 269, "type": "ending"}, {"x": 448, "y": 275, "type": "ending"}, {"x": 448, "y": 358, "type": "bifurcation"}, {"x": 448, "y": 368, "type": "ending"}, {"x": 448, "y": 395, "type": "ending"}, {"x": 448, "y": 443, "type": "bifurcation"}, {"x": 449, "y": 89, "type": "bifurcation"}, {"x": 449, "y": 315, "type": "bifurcation"}, {"x": 450, "y": 136, "type": "ending"}, {"x": 450, "y": 312, "type": "ending"}, {"x": 450, "y": 358, "type": "ending"}, {"x": 450, "y": 408, "type": "bifurcation"}, {"x": 450, "y": 444, "type": "ending"}, {"x": 451, "y": 223, "type": "bifurcation"}, {"x": 451, "y": 434, "type": "bifurcation"}, {"x": 452, "y": 61, "type": "bifurcation"}, {"x": 452, "y": 67, "type": "bifurcation"}, {"x": 452, "y": 200, "type": "bifurcation"}, {"x": 452, "y": 343, "type": "bifurcation"}, {"x": 452, "y": 408, "type": "ending"}, {"x": 453, "y": 427, "type": "bifurcation"}, {"x": 454, "y": 344, "type": "ending"}, {"x": 454, "y": 434, "type": "ending"}, {"x": 454, "y": 449, "type": "ending"}, {"x": 455, "y": 53, "type": "ending"}, {"x": 456, "y": 84, "type": "ending"}, {"x": 456, "y": 109, "type": "ending"}, {"x": 456, "y": 426, "type": "ending"}, {"x": 457, "y": 71, "type": "bifurcation"}, {"x": 458, "y": 126, "type": "bifurcation"}, {"x": 458, "y": 168, "type": "bifurcation"}, {"x": 458, "y": 385, "type": "bifurcation"}, {"x": 458, "y": 414, "type": "bifurcation"}, {"x": 458, "y": 434, "type": "ending"}, {"x": 458, "y": 443, "type": "bifurcation"}, {"x": 459, "y": 56, "type": "ending"}, {"x": 459, "y": 133, "type": "bifurcation"}, {"x": 459, "y": 385, "type": "bifurcation"}, {"x": 460, "y": 55, "type": "bifurcation"}, {"x": 460, "y": 64, "type": "ending"}, {"x": 460, "y": 77, "type": "bifurcation"}, {"x": 460, "y": 80, "type": "ending"}, {"x": 460, "y": 83, "type": "ending"}, {"x": 460, "y": 121, "type": "bifurcation"}, {"x": 460, "y": 126, "type": "bifurcation"}, {"x": 460, "y": 168, "type": "bifurcation"}, {"x": 460, "y": 196, "type": "ending"}, {"x": 460, "y": 269, "type": "ending"}, {"x": 460, "y": 368, "type": "ending"}, {"x": 460, "y": 387, "type": "ending"}, {"x": 460, "y": 414, "type": "ending"}, {"x": 460, "y": 427, "type": "ending"}, {"x": 461, "y": 169, "type": "bifurcation"}, {"x": 462, "y": 66, "type": "ending"}, {"x": 462, "y": 69, "type": "bifurcation"}, {"x": 462, "y": 286, "type": "bifurcation"}, {"x": 462, "y": 384, "type": "ending"}, {"x": 462, "y": 397, "type": "bifurcation"}, {"x": 462, "y": 399, "type": "bifurcation"}, {"x": 462, "y": 444, "type": "ending"}, {"x": 463, "y": 103, "type": "ending"}, {"x": 463, "y": 396, "type": "bifurcation"}, {"x": 463, "y": 403, "type": "bifurcation"}, {"x": 464, "y": 63, "type": "ending"}, {"x": 464, "y": 109, "type": "bifurcation"}, {"x": 464, "y": 168, "type": "ending"}, {"x": 464, "y": 286, "type": "ending"}, {"x": 464, "y": 415, "type": "ending"}, {"x": 465, "y": 61, "type": "bifurcation"}, {"x": 465, "y": 87, "type": "ending"}, {"x": 465, "y": 97, "type": "ending"}, {"x": 466, "y": 245, "type": "ending"}, {"x": 466, "y": 312, "type": "bifurcation"}, {"x": 466, "y": 449, "type": "ending"}, {"x": 467, "y": 82, "type": "bifurcation"}, {"x": 468, "y": 312, "type": "ending"}, {"x": 468, "y": 400, "type": "bifurcation"}, {"x": 468, "y": 404, "type": "ending"}, {"x": 469, "y": 394, "type": "ending"}, {"x": 469, "y": 397, "type": "bifurcation"}, {"x": 469, "y": 401, "type": "bifurcation"}, {"x": 470, "y": 89, "type": "ending"}, {"x": 470, "y": 94, "type": "ending"}, {"x": 470, "y": 296, "type": "bifurcation"}, {"x": 470, "y": 395, "type": "bifurcation"}, {"x": 470, "y": 396, "type": "bifurcation"}, {"x": 470, "y": 403, "type": "ending"}, {"x": 470, "y": 433, "type": "ending"}, {"x": 470, "y": 439, "type": "ending"}, {"x": 471, "y": 87, "type": "bifurcation"}, {"x": 471, "y": 378, "type": "bifurcation"}, {"x": 472, "y": 91, "type": "ending"}, {"x": 472, "y": 187, "type": "ending"}, {"x": 472, "y": 278, "type": "bifurcation"}, {"x": 472, "y": 296, "type": "ending"}, {"x": 473, "y": 88, "type": "bifurcation"}, {"x": 473, "y": 89, "type": "bifurcation"}, {"x": 473, "y": 352, "type": "bifurcation"}, {"x": 473, "y": 408, "type": "bifurcation"}, {"x": 474, "y": 278, "type": "ending"}, {"x": 474, "y": 294, "type": "ending"}, {"x": 474, "y": 381, "type": "ending"}, {"x": 474, "y": 419, "type": "bifurcation"}, {"x": 474, "y": 444, "type": "ending"}, {"x": 474, "y": 448, "type": "ending"}, {"x": 475, "y": 87, "type": "ending"}, {"x": 475, "y": 379, "type": "bifurcation"}, {"x": 475, "y": 435, "type": "bifurcation"}, {"x": 476, "y": 52, "type": "ending"}, {"x": 476, "y": 62, "type": "ending"}, {"x": 476, "y": 350, "type": "ending"}, {"x": 476, "y": 388, "type": "ending"}, {"x": 476, "y": 412, "type": "ending"}, {"x": 476, "y": 418, "type": "ending"}, {"x": 477, "y": 412, "type": "ending"}, {"x": 477, "y": 422, "type": "bifurcation"}, {"x": 478, "y": 286, "type": "bifurcation"}, {"x": 478, "y": 318, "type": "ending"}, {"x": 478, "y": 354, "type": "ending"}, {"x": 478, "y": 409, "type": "bifurcation"}, {"x": 480, "y": 53, "type": "ending"}, {"x": 480, "y": 56, "type": "ending"}, {"x": 480, "y": 58, "type": "ending"}, {"x": 480, "y": 82, "type": "ending"}, {"x": 480, "y": 423, "type": "bifurcation"}, {"x": 480, "y": 426, "type": "ending"}, {"x": 481, "y": 377, "type": "bifurcation"}, {"x": 481, "y": 407, "type": "bifurcation"}, {"x": 482, "y": 360, "type": "ending"}, {"x": 482, "y": 366, "type": "ending"}, {"x": 482, "y": 379, "type": "ending"}, {"x": 482, "y": 409, "type": "bifurcation"}, {"x": 483, "y": 71, "type": "bifurcation"}, {"x": 483, "y": 350, "type": "bifurcation"}, {"x": 484, "y": 54, "type": "ending"}, {"x": 484, "y": 92, "type": "ending"}, {"x": 485, "y": 58, "type": "ending"}, {"x": 485, "y": 63, "type": "bifurcation"}, {"x": 485, "y": 266, "type": "bifurcation"}, {"x": 486, "y": 70, "type": "ending"}, {"x": 486, "y": 100, "type": "ending"}, {"x": 486, "y": 342, "type": "bifurcation"}, {"x": 486, "y": 350, "type": "ending"}, {"x": 486, "y": 444, "type": "ending"}, {"x": 487, "y": 60, "type": "bifurcation"}, {"x": 488, "y": 63, "type": "ending"}, {"x": 488, "y": 84, "type": "ending"}, {"x": 488, "y": 94, "type": "ending"}, {"x": 488, "y": 379, "type": "ending"}, {"x": 489, "y": 81, "type": "bifurcation"}, {"x": 489, "y": 294, "type": "bifurcation"}, {"x": 490, "y": 64, "type": "ending"}, {"x": 490, "y": 281, "type": "ending"}, {"x": 490, "y": 308, "type": "ending"}, {"x": 490, "y": 331, "type": "bifurcation"}, {"x": 491, "y": 83, "type": "bifurcation"}, {"x": 492, "y": 74, "type": "ending"}, {"x": 492, "y": 149, "type": "bifurcation"}, {"x": 492, "y": 352, "type": "ending"}, {"x": 493, "y": 288, "type": "bifurcation"}, {"x": 494, "y": 72, "type": "ending"}, {"x": 494, "y": 151, "type": "ending"}, {"x": 495, "y": 81, "type": "bifurcation"}, {"x": 495, "y": 95, "type": "bifurcation"}, {"x": 495, "y": 392, "type": "bifurcation"}, {"x": 496, "y": 90, "type": "ending"}, {"x": 496, "y": 185, "type": "bifurcation"}, {"x": 496, "y": 211, "type": "bifurcation"}, {"x": 496, "y": 292, "type": "bifurcation"}, {"x": 496, "y": 324, "type": "ending"}, {"x": 496, "y": 432, "type": "ending"}, {"x": 497, "y": 386, "type": "bifurcation"}, {"x": 497, "y": 389, "type": "bifurcation"}, {"x": 497, "y": 423, "type": "ending"}, {"x": 498, "y": 81, "type": "bifurcation"}, {"x": 498, "y": 146, "type": "ending"}, {"x": 498, "y": 184, "type": "ending"}, {"x": 498, "y": 210, "type": "ending"}, {"x": 498, "y": 312, "type": "bifurcation"}, {"x": 498, "y": 340, "type": "ending"}, {"x": 498, "y": 387, "type": "bifurcation"}, {"x": 498, "y": 391, "type": "bifurcation"}, {"x": 498, "y": 416, "type": "ending"}, {"x": 499, "y": 403, "type": "bifurcation"}, {"x": 500, "y": 54, "type": "bifurcation"}, {"x": 500, "y": 60, "type": "ending"}, {"x": 500, "y": 156, "type": "bifurcation"}, {"x": 500, "y": 329, "type": "bifurcation"}, {"x": 501, "y": 84, "type": "bifurcation"}, {"x": 501, "y": 146, "type": "bifurcation"}, {"x": 501, "y": 279, "type": "bifurcation"}, {"x": 501, "y": 389, "type": "bifurcation"}, {"x": 502, "y": 80, "type": "ending"}, {"x": 502, "y": 145, "type": "bifurcation"}, {"x": 502, "y": 147, "type": "bifurcation"}, {"x": 502, "y": 174, "type": "ending"}, {"x": 502, "y": 281, "type": "ending"}, {"x": 502, "y": 304, "type": "bifurcation"}, {"x": 502, "y": 305, "type": "bifurcation"}, {"x": 503, "y": 54, "type": "bifurcation"}, {"x": 503, "y": 55, "type": "bifurcation"}, {"x": 503, "y": 86, "type": "bifurcation"}, {"x": 503, "y": 143, "type": "bifurcation"}, {"x": 503, "y": 146, "type": "bifurcation"}, {"x": 503, "y": 191, "type": "ending"}, {"x": 503, "y": 260, "type": "ending"}, {"x": 504, "y": 60, "type": "ending"}, {"x": 504, "y": 80, "type": "ending"}, {"x": 504, "y": 307, "type": "ending"}, {"x": 504, "y": 330, "type": "ending"}, {"x": 504, "y": 334, "type": "ending"}, {"x": 504, "y": 340, "type": "ending"}, {"x": 504, "y": 344, "type": "bifurcation"}, {"x": 504, "y": 381, "type": "ending"}, {"x": 505, "y": 87, "type": "bifurcation"}, {"x": 505, "y": 175, "type": "bifurcation"}, {"x": 505, "y": 210, "type": "bifurcation"}, {"x": 505, "y": 272, "type": "bifurcation"}, {"x": 506, "y": 144, "type": "ending"}, {"x": 506, "y": 147, "type": "ending"}, {"x": 506, "y": 164, "type": "bifurcation"}, {"x": 507, "y": 54, "type": "bifurcation"}, {"x": 508, "y": 97, "type": "bifurcation"}, {"x": 508, "y": 100, "type": "ending"}, {"x": 508, "y": 150, "type": "ending"}, {"x": 508, "y": 177, "type": "ending"}, {"x": 508, "y": 210, "type": "ending"}, {"x": 508, "y": 313, "type": "bifurcation"}, {"x": 509, "y": 54, "type": "bifurcation"}, {"x": 509, "y": 175, "type": "bifurcation"}, {"x": 510, "y": 410, "type": "ending"}, {"x": 511, "y": 53, "type": "ending"}, {"x": 511, "y": 98, "type": "bifurcation"}, {"x": 511, "y": 133, "type": "ending"}, {"x": 511, "y": 159, "type": "bifurcation"}, {"x": 511, "y": 176, "type": "bifurcation"}, {"x": 511, "y": 180, "type": "ending"}, {"x": 511, "y": 273, "type": "bifurcation"}, {"x": 512, "y": 56, "type": "ending"}, {"x": 512, "y": 91, "type": "ending"}, {"x": 512, "y": 158, "type": "bifurcation"}, {"x": 512, "y": 180, "type": "bifurcation"}, {"x": 512, "y": 275, "type": "ending"}, {"x": 513, "y": 88, "type": "bifurcation"}, {"x": 513, "y": 89, "type": "bifurcation"}, {"x": 514, "y": 58, "type": "ending"}, {"x": 514, "y": 60, "type": "bifurcation"}, {"x": 514, "y": 96, "type": "ending"}, {"x": 514, "y": 142, "type": "bifurcation"}, {"x": 514, "y": 157, "type": "ending"}, {"x": 514, "y": 256, "type": "ending"}, {"x": 514, "y": 371, "type": "bifurcation"}, {"x": 514, "y": 402, "type": "ending"}, {"x": 514, "y": 408, "type": "ending"}, {"x": 515, "y": 287, "type": "bifurcation"}, {"x": 516, "y": 91, "type": "bifurcation"}, {"x": 516, "y": 404, "type": "ending"}, {"x": 517, "y": 87, "type": "bifurcation"}, {"x": 517, "y": 90, "type": "bifurcation"}, {"x": 517, "y": 139, "type": "bifurcation"}, {"x": 517, "y": 156, "type": "ending"}, {"x": 517, "y": 289, "type": "bifurcation"}, {"x": 518, "y": 68, "type": "ending"}, {"x": 518, "y": 131, "type": "bifurcation"}, {"x": 518, "y": 149, "type": "bifurcation"}, {"x": 518, "y": 181, "type": "ending"}, {"x": 518, "y": 192, "type": "ending"}, {"x": 518, "y": 292, "type": "ending"}, {"x": 518, "y": 320, "type": "ending"}, {"x": 518, "y": 322, "type": "bifurcation"}, {"x": 518, "y": 410, "type": "ending"}, {"x": 519, "y": 53, "type": "ending"}, {"x": 519, "y": 179, "type": "bifurcation"}, {"x": 519, "y": 201, "type": "ending"}, {"x": 519, "y": 277, "type": "ending"}, {"x": 520, "y": 70, "type": "ending"}, {"x": 520, "y": 72, "type": "bifurcation"}, {"x": 520, "y": 176, "type": "ending"}, {"x": 520, "y": 179, "type": "bifurcation"}, {"x": 521, "y": 55, "type": "ending"}, {"x": 521, "y": 92, "type": "ending"}, {"x": 522, "y": 106, "type": "ending"}, {"x": 522, "y": 196, "type": "ending"}, {"x": 522, "y": 290, "type": "ending"}, {"x": 522, "y": 387, "type": "ending"}, {"x": 523, "y": 101, "type": "bifurcation"}, {"x": 523, "y": 200, "type": "ending"}, {"x": 523, "y": 203, "type": "bifurcation"}, {"x": 524, "y": 105, "type": "ending"}, {"x": 524, "y": 272, "type": "bifurcation"}, {"x": 524, "y": 293, "type": "ending"}, {"x": 524, "y": 384, "type": "bifurcation"}, {"x": 525, "y": 175, "type": "ending"}, {"x": 525, "y": 190, "type": "bifurcation"}, {"x": 526, "y": 68, "type": "ending"}, {"x": 526, "y": 91, "type": "ending"}, {"x": 526, "y": 100, "type": "bifurcation"}, {"x": 526, "y": 266, "type": "bifurcation"}, {"x": 526, "y": 284, "type": "ending"}, {"x": 526, "y": 292, "type": "bifurcation"}, {"x": 526, "y": 320, "type": "bifurcation"}, {"x": 527, "y": 61, "type": "ending"}, {"x": 527, "y": 89, "type": "bifurcation"}, {"x": 527, "y": 125, "type": "bifurcation"}, {"x": 527, "y": 261, "type": "bifurcation"}, {"x": 527, "y": 266, "type": "ending"}, {"x": 527, "y": 291, "type": "bifurcation"}, {"x": 527, "y": 321, "type": "bifurcation"}, {"x": 527, "y": 340, "type": "bifurcation"}, {"x": 528, "y": 68, "type": "ending"}, {"x": 528, "y": 73, "type": "ending"}, {"x": 528, "y": 81, "type": "ending"}, {"x": 528, "y": 89, "type": "ending"}, {"x": 528, "y": 98, "type": "ending"}, {"x": 528, "y": 104, "type": "ending"}, {"x": 528, "y": 125, "type": "ending"}, {"x": 528, "y": 128, "type": "ending"}, {"x": 528, "y": 134, "type": "ending"}, {"x": 528, "y": 141, "type": "ending"}, {"x": 528, "y": 151, "type": "ending"}, {"x": 528, "y": 162, "type": "ending"}, {"x": 528, "y": 169, "type": "ending"}, {"x": 528, "y": 176, "type": "ending"}, {"x": 528, "y": 179, "type": "ending"}, {"x": 528, "y": 188, "type": "ending"}, {"x": 528, "y": 196, "type": "ending"}, {"x": 528, "y": 257, "type": "ending"}, {"x": 528, "y": 263, "type": "ending"}, {"x": 528, "y": 274, "type": "ending"}, {"x": 528, "y": 289, "type": "ending"}, {"x": 528, "y": 292, "type": "ending"}, {"x": 528, "y": 294, "type": "ending"}, {"x": 528, "y": 301, "type": "ending"}, {"x": 528, "y": 308, "type": "ending"}, {"x": 528, "y": 318, "type": "ending"}, {"x": 528, "y": 322, "type": "ending"}, {"x": 528, "y": 331, "type": "ending"}, {"x": 528, "y": 339, "type": "ending"}, {"x": 528, "y": 342, "type": "ending"}, {"x": 528, "y": 348, "type": "ending"}, {"x": 528, "y": 357, "type": "ending"}, {"x": 528, "y": 364, "type": "ending"}, {"x": 528, "y": 372, "type": "ending"}, {"x": 528, "y": 382, "type": "ending"}, {"x": 528, "y": 391, "type": "ending"}, {"x": 528, "y": 400, "type": "ending"}, {"x": 528, "y": 402, "type": "ending"}, {"x": 528, "y": 403, "type": "ending"}, {"x": 528, "y": 408, "type": "ending"}, {"x": 435, "y": 75, "type": "bifurcation"}]}